{"namespace":"thrive-product-manager\/v1","routes":{"\/thrive-product-manager\/v1":{"namespace":"thrive-product-manager\/v1","methods":["GET"],"endpoints":[{"methods":["GET"],"args":{"namespace":{"default":"thrive-product-manager\/v1","required":false},"context":{"default":"view","required":false},"wpml_language":{"type":"string","description":"WPML's language code","enum":["en","es"],"required":false}}}],"_links":{"self":[{"href":"https:\/\/staging.bodhimedicine.com\/wp-json\/thrive-product-manager\/v1"}]}},"\/thrive-product-manager\/v1\/deactivate\/(?P<id>\\d+)":{"namespace":"thrive-product-manager\/v1","methods":["POST"],"endpoints":[{"methods":["POST"],"args":{"wpml_language":{"type":"string","description":"WPML's language code","enum":["en","es"],"required":false}}}]}},"_links":{"up":[{"href":"https:\/\/staging.bodhimedicine.com\/wp-json\/"}]}}